README.md
nano_code/__init__.py
nano_code/__main__.py
nano_code/constants.py
nano_code/env.py
nano_code/agent/non_interactive_agent.py
nano_code/agent_tool/__init__.py
nano_code/agent_tool/base.py
nano_code/agent_tool/registry.py
nano_code/agent_tool/tool_schema.py
nano_code/agent_tool/tools.py
nano_code/agent_tool/os_tool/__init__.py
nano_code/agent_tool/os_tool/create_file.py
nano_code/agent_tool/os_tool/edit_file.py
nano_code/agent_tool/os_tool/find_files.py
nano_code/agent_tool/os_tool/list_dir.py
nano_code/agent_tool/os_tool/mv_file_or_dir.py
nano_code/agent_tool/os_tool/read_file.py
nano_code/agent_tool/os_tool/search_text.py
nano_code/agent_tool/util_tool/add_tasks.py
nano_code/core/cost.py
nano_code/core/session.py
nano_code/llm/__init__.py
nano_code/llm/clients.py
nano_code/llm/openai_model.py
nano_code/utils/file.py
nano_code/utils/logger.py
nano_code/utils/paths.py
nano_code/utils/tokens.py
nano_code-0.1.5.dist-info/METADATA
nano_code-0.1.5.dist-info/WHEEL
nano_code-0.1.5.dist-info/entry_points.txt
nano_code-0.1.5.dist-info/RECORD
