Metadata-Version: 2.4
Name: nano-code
Version: 0.1.5
Summary: A Python Implementation of Gemini Code
Requires-Python: >=3.11
Requires-Dist: gitignore-parser>=0.1.12
Requires-Dist: openai>=1.92.2
Requires-Dist: rich>=14.0.0
Requires-Dist: tiktoken>=0.9.0
